{
  "id" : "0734d74b221ff5d33bf659e8ba06d74e2abe807a73ba3e58aae277f1960aa610",
  "baseType" : "Leather Belt",
  "rarity" : "Rare",
  "ilvl" : 85,
  "identified" : true,
  "extended" : {
    "category" : "accessories"
  },
  "note" : "~price 50 chaos",
  "implicitMods" : [ "+34 to maximum Life" ],
  "explicitMods" : [ "+35 to Strength", "28% increased Stun and Block Recovery", "39% increased Flask Charges gained" ],
  "requirements" : [ {
    "name" : "Level",
    "values" : [ [ "67", 0 ] ]
  } ],
  "properties" : null,
  "enchantMods" : null,
  "craftedMods" : null,
  "fracturedMods" : [ "+92 to maximum Life" ],
  "veiledMods" : null,
  "sockets" : null,
  "fractured" : true,
  "synthesised" : false,
  "duplicated" : false,
  "split" : false,
  "corrupted" : false,
  "influences" : null,
  "accessories" : true,
  "notUnique" : true
}