{
  "id" : "126794cf5296f549c1bd31f7a06adc9876e00272bdc9ced07f7c095970147a6c",
  "baseType" : "Unset Ring",
  "rarity" : "Magic",
  "ilvl" : 83,
  "identified" : true,
  "extended" : {
    "category" : "accessories"
  },
  "note" : "~price 5 chaos",
  "implicitMods" : [ "Has 1 Socket" ],
  "explicitMods" : [ "+45 to Dexterity" ],
  "requirements" : [ {
    "name" : "Level",
    "values" : [ [ "59", 0 ] ]
  } ],
  "properties" : null,
  "enchantMods" : null,
  "craftedMods" : null,
  "fracturedMods" : [ "+15 to maximum Energy Shield" ],
  "veiledMods" : null,
  "sockets" : [ {
    "group" : 0,
    "sColour" : "B"
  } ],
  "fractured" : true,
  "synthesised" : false,
  "duplicated" : false,
  "split" : false,
  "corrupted" : false,
  "influences" : null,
  "accessories" : true,
  "notUnique" : true
}