{
  "id" : "3e71de3bdf8e5ca15d437e3b280b87b957a9d514d968850074236b0890275a07",
  "baseType" : "Lapis Amulet",
  "rarity" : "Rare",
  "ilvl" : 77,
  "identified" : true,
  "extended" : {
    "category" : "accessories"
  },
  "note" : "~b/o 31 chaos",
  "implicitMods" : [ "+26 to Intelligence" ],
  "explicitMods" : [ "+28 to all Attributes", "+32 to Strength", "Adds 7 to 11 Physical Damage to Attacks" ],
  "requirements" : [ {
    "name" : "Level",
    "values" : [ [ "52", 0 ] ]
  } ],
  "properties" : null,
  "enchantMods" : null,
  "craftedMods" : null,
  "fracturedMods" : null,
  "veiledMods" : [ "Prefix03" ],
  "sockets" : null,
  "fractured" : false,
  "synthesised" : false,
  "duplicated" : false,
  "split" : false,
  "corrupted" : false,
  "influences" : null,
  "accessories" : true,
  "notUnique" : true
}