{
  "id" : "4ce0962332bc53ea43e39c0fc9d7b55613b2494783498a65ad5d81b716f47664",
  "baseType" : "Two-Stone Ring",
  "rarity" : "Rare",
  "ilvl" : 83,
  "identified" : true,
  "extended" : {
    "category" : "accessories"
  },
  "note" : "~price 6 chaos",
  "implicitMods" : [ "+15% to Fire and Cold Resistances" ],
  "explicitMods" : [ "+17 to Strength", "+34 to maximum Life", "13% increased Rarity of Items found" ],
  "requirements" : [ {
    "name" : "Level",
    "values" : [ [ "40", 0 ] ]
  } ],
  "properties" : null,
  "enchantMods" : null,
  "craftedMods" : null,
  "fracturedMods" : [ "0.2% of Physical Attack Damage Leeched as Mana" ],
  "veiledMods" : null,
  "sockets" : null,
  "fractured" : true,
  "synthesised" : false,
  "duplicated" : false,
  "split" : false,
  "corrupted" : false,
  "influences" : null,
  "accessories" : true,
  "notUnique" : true
}