{
  "id" : "67a44a5f83034887815a82ae0f11c4f2b489c0588e46dbe7ead8c767ce3b9308",
  "baseType" : "Unset Ring",
  "rarity" : "Rare",
  "ilvl" : 78,
  "identified" : true,
  "extended" : {
    "category" : "accessories"
  },
  "note" : "~price 10 chaos",
  "implicitMods" : [ "Has 1 Socket" ],
  "explicitMods" : [ "+10 to Intelligence", "10% increased Lightning Damage", "+19 to Evasion Rating", "+75 to maximum Life" ],
  "requirements" : [ {
    "name" : "Level",
    "values" : [ [ "35", 0 ] ]
  } ],
  "properties" : null,
  "enchantMods" : null,
  "craftedMods" : null,
  "fracturedMods" : null,
  "veiledMods" : null,
  "sockets" : [ {
    "group" : 0,
    "sColour" : "G"
  } ],
  "fractured" : false,
  "synthesised" : false,
  "duplicated" : false,
  "split" : false,
  "corrupted" : false,
  "influences" : null,
  "accessories" : true,
  "notUnique" : true
}