{
  "id" : "7867fdd9d93c270837a78cabbc807639518197865d0345ab0d93931e341cd5c6",
  "baseType" : "Unset Ring",
  "rarity" : "Rare",
  "ilvl" : 80,
  "identified" : true,
  "extended" : {
    "category" : "accessories"
  },
  "note" : "~b/o 23 chaos",
  "implicitMods" : [ "Has 1 Socket" ],
  "explicitMods" : [ "+36 to Intelligence", "22% increased Cold Damage", "+94 to Evasion Rating", "+41% to Fire Resistance", "Channelling Skills have -4 to Total Mana Cost" ],
  "requirements" : [ {
    "name" : "Level",
    "values" : [ [ "48", 0 ] ]
  } ],
  "properties" : null,
  "enchantMods" : null,
  "craftedMods" : null,
  "fracturedMods" : null,
  "veiledMods" : null,
  "sockets" : [ {
    "group" : 0,
    "sColour" : "R"
  } ],
  "fractured" : false,
  "synthesised" : false,
  "duplicated" : false,
  "split" : false,
  "corrupted" : false,
  "influences" : null,
  "accessories" : true,
  "notUnique" : true
}