{
  "id" : "8c65b5e2b335517284eb7df67161deae6641f2c225fd080e17637e756a7f5d32",
  "baseType" : "Unset Ring",
  "rarity" : "Rare",
  "ilvl" : 85,
  "identified" : true,
  "extended" : {
    "category" : "accessories"
  },
  "note" : "~b/o 10 chaos",
  "implicitMods" : [ "Has 1 Socket" ],
  "explicitMods" : [ "Adds 1 to 2 Fire Damage to Attacks", "+1 to maximum Energy Shield", "+14% to all Elemental Resistances", "+37% to Lightning Resistance", "+34% to Chaos Resistance", "9% increased Elemental Damage with Attack Skills" ],
  "requirements" : [ {
    "name" : "Level",
    "values" : [ [ "64", 0 ] ]
  } ],
  "properties" : null,
  "enchantMods" : null,
  "craftedMods" : null,
  "fracturedMods" : null,
  "veiledMods" : null,
  "sockets" : [ {
    "group" : 0,
    "sColour" : "R"
  } ],
  "fractured" : false,
  "synthesised" : false,
  "duplicated" : false,
  "split" : false,
  "corrupted" : false,
  "influences" : null,
  "accessories" : true,
  "notUnique" : true
}