{
  "id" : "c57615fea3b00e5fe483cb9d2381b0f1bc372f9e9b8dc9843a384fff45de04f2",
  "baseType" : "Stygian Vise",
  "rarity" : "Rare",
  "ilvl" : 85,
  "identified" : true,
  "extended" : {
    "category" : "accessories"
  },
  "note" : "~b/o 20 chaos",
  "implicitMods" : [ "Has 1 Abyssal Socket" ],
  "explicitMods" : [ "+26 to Strength", "+44 to maximum Mana", "+26% to Lightning Resistance", "29% increased Flask Charges gained" ],
  "requirements" : [ {
    "name" : "Level",
    "values" : [ [ "56", 0 ] ]
  } ],
  "properties" : null,
  "enchantMods" : null,
  "craftedMods" : null,
  "fracturedMods" : null,
  "veiledMods" : null,
  "sockets" : [ {
    "group" : 0,
    "sColour" : "A"
  } ],
  "fractured" : false,
  "synthesised" : false,
  "duplicated" : false,
  "split" : false,
  "corrupted" : false,
  "influences" : null,
  "accessories" : true,
  "notUnique" : true
}