{
  "id" : "e88f06c08d4ce0cc7bc31f33ab3c524ce3cd7cfaf358b26c079116b576a2a7d5",
  "baseType" : "Unset Ring",
  "rarity" : "Rare",
  "ilvl" : 73,
  "identified" : true,
  "extended" : {
    "category" : "accessories"
  },
  "note" : "~price 6 chaos",
  "implicitMods" : [ "Has 1 Socket" ],
  "explicitMods" : [ "+9 to Strength", "10% increased Lightning Damage", "+3 to Evasion Rating", "+40% to Lightning Resistance" ],
  "requirements" : [ {
    "name" : "Level",
    "values" : [ [ "48", 0 ] ]
  } ],
  "properties" : null,
  "enchantMods" : null,
  "craftedMods" : null,
  "fracturedMods" : null,
  "veiledMods" : null,
  "sockets" : [ {
    "group" : 0,
    "sColour" : "G"
  } ],
  "fractured" : false,
  "synthesised" : false,
  "duplicated" : false,
  "split" : false,
  "corrupted" : false,
  "influences" : null,
  "accessories" : true,
  "notUnique" : true
}