{
  "id" : "e92016c20ec9f10ab92622ccf0585dd547f1d428be8795a924ae20e701909fcd",
  "baseType" : "Unset Ring",
  "rarity" : "Rare",
  "ilvl" : 72,
  "identified" : true,
  "extended" : {
    "category" : "accessories"
  },
  "note" : "~price 3 chaos 7",
  "implicitMods" : [ "Has 1 Socket" ],
  "explicitMods" : [ "Adds 4 to 10 Physical Damage to Attacks", "11% increased Cold Damage", "+14 to Evasion Rating", "+11 to maximum Life" ],
  "requirements" : [ {
    "name" : "Level",
    "values" : [ [ "22", 0 ] ]
  } ],
  "properties" : null,
  "enchantMods" : null,
  "craftedMods" : null,
  "fracturedMods" : null,
  "veiledMods" : null,
  "sockets" : [ {
    "group" : 0,
    "sColour" : "B"
  } ],
  "fractured" : false,
  "synthesised" : false,
  "duplicated" : false,
  "split" : false,
  "corrupted" : false,
  "influences" : null,
  "accessories" : true,
  "notUnique" : true
}